{
  "Hawaii": 2.0,
  "North Dakota": 2.6,
  "Iowa": 2.7,
  "New Hampshire": 2.7,
  "Colorado": 2.8,
  "Maine": 2.8,
  "Nebraska": 2.8,
  "Vermont": 2.8,
  "Wisconsin": 2.8,
  "Idaho": 2.9,
  "Utah": 3.0,
  "Minnesota": 3.1,
  "Indiana": 3.2,
  "Virginia": 3.2,
  "South Dakota": 3.3,
  "Kansas": 3.4,
  "Massachusetts": 3.5,
  "Tennessee": 3.5,
  "Missouri": 3.6,
  "Wyoming": 3.7,
  "Arkansas": 3.8,
  "Florida": 3.8,
  "Alabama": 3.9,
  "Montana": 3.9,
  "Delaware": 4.0,
  "Oklahoma": 4.0,
  "South Carolina": 4.0,
  "Kentucky": 4.1,
  "Oregon": 4.1,
  "Texas": 4.1,
  "California": 4.2,
  "Georgia": 4.2,
  "Illinois": 4.3,
  "Maryland": 4.3,
  "North Carolina": 4.3,
  "Ohio": 4.3,
  "New Jersey": 4.4,
  "Rhode Island": 4.4,
  "Connecticut": 4.5,
  "New York": 4.5,
  "Pennsylvania": 4.5,
  "Louisiana": 4.6,
  "Michigan": 4.6,
  "Arizona": 4.7,
  "Mississippi": 4.7,
  "Washington": 4.7,
  "Nevada": 4.8,
  "New Mexico": 5.1,
  "West Virginia": 5.4,
  "District of Columbia": 5.6,
  "Alaska": 7.2
}
